TracCrystalXTheme-1.1.dist-info/DESCRIPTION.rst
TracCrystalXTheme-1.1.dist-info/METADATA
TracCrystalXTheme-1.1.dist-info/RECORD
TracCrystalXTheme-1.1.dist-info/WHEEL
TracCrystalXTheme-1.1.dist-info/entry_points.txt
TracCrystalXTheme-1.1.dist-info/metadata.json
TracCrystalXTheme-1.1.dist-info/top_level.txt
crystalxtheme/__init__.py
crystalxtheme/theme.py
crystalxtheme/htdocs/crystalx.css
crystalxtheme/htdocs/screenshot.png
crystalxtheme/htdocs/img/bg.gif
crystalxtheme/htdocs/img/bg_page.gif
crystalxtheme/htdocs/img/bg_page_in.jpg
crystalxtheme/htdocs/img/btn_more.gif
crystalxtheme/htdocs/img/col_bg.gif
crystalxtheme/htdocs/img/col_title_bg.gif
crystalxtheme/htdocs/img/col_top.gif
crystalxtheme/htdocs/img/content_article_bg.jpg
crystalxtheme/htdocs/img/content_title_bg.gif
crystalxtheme/htdocs/img/footer.jpg
crystalxtheme/htdocs/img/header.jpg
crystalxtheme/htdocs/img/ico_archive.gif
crystalxtheme/htdocs/img/ico_archive2.gif
crystalxtheme/htdocs/img/ico_cat.gif
crystalxtheme/htdocs/img/ico_comments.gif
crystalxtheme/htdocs/img/ico_date.gif
crystalxtheme/htdocs/img/ico_links.gif
crystalxtheme/htdocs/img/ico_list.gif
crystalxtheme/htdocs/img/ico_rss.gif
crystalxtheme/htdocs/img/ico_top.gif
crystalxtheme/htdocs/img/ico_user.gif
crystalxtheme/htdocs/img/search_input.gif
crystalxtheme/htdocs/img/search_submit.gif
crystalxtheme/htdocs/img/tab_active_l.gif
crystalxtheme/htdocs/img/tab_active_r.gif
crystalxtheme/htdocs/img/tab_hover.gif
crystalxtheme/htdocs/img/tab_hover_l.gif
crystalxtheme/htdocs/img/tab_hover_r.gif
crystalxtheme/htdocs/img/tab_link.gif
crystalxtheme/htdocs/img/tab_link_l.gif
crystalxtheme/htdocs/img/tab_link_r.gif
crystalxtheme/htdocs/img/tmp_photo.gif
crystalxtheme/templates/crystalx_theme.html
